powerlog/__init__.py
powerlog/__main__.py
powerlog/core.py
powerlog-0.0.2.dist-info/METADATA
powerlog-0.0.2.dist-info/WHEEL
powerlog-0.0.2.dist-info/entry_points.txt
powerlog-0.0.2.dist-info/licenses/LICENSE
powerlog-0.0.2.dist-info/RECORD
