Metadata-Version: 2.4
Name: powerlog
Version: 0.0.2
Summary: GPU power log
Project-URL: Homepage, https://github.com/arsho/powerlog
Project-URL: Issues, https://github.com/arsho/powerlog/issues
Author-email: Ahmedur Rahman Shovon <shovon.sylhet@gmail.com>
License-Expression: MIT
License-File: LICENSE
Keywords: energy,gpupower,power analysis,power log,powerlog
Classifier: Development Status :: 4 - Beta
Classifier: Operating System :: OS Independent
Classifier: Programming Language :: Python :: 3
Requires-Python: >=3.8
